pydilite/__init__.py
pydilite/container.py
pydilite/exceptions.py
pydilite/provider.py
pydilite-0.1.3.dist-info/LICENSE
pydilite-0.1.3.dist-info/METADATA
pydilite-0.1.3.dist-info/WHEEL
pydilite-0.1.3.dist-info/RECORD
