Metadata-Version: 2.1
Name: pydilite
Version: 0.1.3
Summary: Python lightweight dependency injection framework
Author: impalah
Author-email: impalah@gmail.com
Requires-Python: >=3.12,<4.0
Classifier: Programming Language :: Python :: 3
Classifier: Programming Language :: Python :: 3.12
